zpywallet/__init__.py
zpywallet/_version.py
zpywallet/bip38.py
zpywallet/destination.py
zpywallet/errors.py
zpywallet/network.py
zpywallet/transaction.py
zpywallet/utxo.py
zpywallet/wallet.py
zpywallet/address/__init__.py
zpywallet/address/bcy/__init__.py
zpywallet/address/bcy/blockcypher.py
zpywallet/address/bcy/loadbalancer.py
zpywallet/address/btc/__init__.py
zpywallet/address/btc/blockchain_info.py
zpywallet/address/btc/blockcypher.py
zpywallet/address/btc/blockstream.py
zpywallet/address/btc/btcdotcom.py
zpywallet/address/btc/esplora.py
zpywallet/address/btc/fullnode.py
zpywallet/address/btc/loadbalancer.py
zpywallet/address/btc/mempoolspace.py
zpywallet/address/btctest/__init__.py
zpywallet/address/btctest/blockcypher.py
zpywallet/address/btctest/blockstream.py
zpywallet/address/btctest/esplora.py
zpywallet/address/btctest/fullnode.py
zpywallet/address/btctest/loadbalancer.py
zpywallet/address/btctest/mempoolspace.py
zpywallet/address/dash/__init__.py
zpywallet/address/dash/blockcypher.py
zpywallet/address/dash/fullnode.py
zpywallet/address/dash/loadbalancer.py
zpywallet/address/doge/__init__.py
zpywallet/address/doge/blockcypher.py
zpywallet/address/doge/dogechain.py
zpywallet/address/doge/loadbalancer.py
zpywallet/address/eth/__init__.py
zpywallet/address/eth/fullnode.py
zpywallet/address/eth/loadbalancer.py
zpywallet/address/ltc/__init__.py
zpywallet/address/ltc/blockcypher.py
zpywallet/address/ltc/fullnode.py
zpywallet/address/ltc/loadbalancer.py
zpywallet/broadcast/__init__.py
zpywallet/broadcast/broadcast.py
zpywallet/broadcast/bcy/__init__.py
zpywallet/broadcast/bcy/all.py
zpywallet/broadcast/bcy/blockcypher.py
zpywallet/broadcast/btc/__init__.py
zpywallet/broadcast/btc/all.py
zpywallet/broadcast/btc/bitaps.py
zpywallet/broadcast/btc/blockchain_info.py
zpywallet/broadcast/btc/blockchair.py
zpywallet/broadcast/btc/blockcypher.py
zpywallet/broadcast/btc/blockstream.py
zpywallet/broadcast/btc/esplora.py
zpywallet/broadcast/btc/fullnode.py
zpywallet-0.6.2.dist-info/AUTHORS
zpywallet-0.6.2.dist-info/LICENSE
zpywallet-0.6.2.dist-info/METADATA
zpywallet-0.6.2.dist-info/WHEEL
zpywallet-0.6.2.dist-info/top_level.txt
zpywallet-0.6.2.dist-info/RECORD
