Metadata-Version: 2.1
Name: zpywallet
Version: 0.6.2
Summary: Multi-coin BIP32 (HD) wallet creation, transaction listener, creation and broadcasting
Home-page: https://github.com/ZenulAbidin/pywallet
Author: Ali Sherief
Author-email: ali@notatether.com
License: MIT License
Keywords: bitcoin,wallet,litecoin,hd-wallet,dogecoin,dashcoin,ethereum,address,crypto,python
Platform: any
Classifier: License :: OSI Approved :: MIT License
Classifier: Development Status :: 4 - Beta
Classifier: Intended Audience :: Developers
Classifier: Operating System :: OS Independent
Classifier: Programming Language :: Python :: 3.8
Classifier: Programming Language :: Python :: 3.9
Classifier: Programming Language :: Python :: 3.10
Classifier: Programming Language :: Python :: 3.11
Classifier: Programming Language :: Python :: 3.12
License-File: LICENSE
License-File: AUTHORS
Requires-Dist: coincurve >=18.0.0
Requires-Dist: cryptography >=39.0.1
Requires-Dist: scrypt >=0.8.20
Requires-Dist: requests >=2.20.1
Requires-Dist: protobuf !=4.24.0,>=4.23.0
Requires-Dist: pycryptodomex >=3.9.2
Requires-Dist: aiohttp <4.0
Requires-Dist: web3 >=6.14.0
Requires-Dist: websocket-client
